wagtail_links/__init__.py
wagtail_links/apps.py
wagtail_links/fields.py
wagtail_links/locale/es/LC_MESSAGES/django.mo
wagtail_links/locale/es/LC_MESSAGES/django.po
wagtail_links/migrations/0001_initial.py
wagtail_links/migrations/0002_auto_20170522_1552.py
wagtail_links/migrations/0003_auto_20170522_2015.py
wagtail_links/migrations/0004_auto_20190411_2102.py
wagtail_links/migrations/0005_auto_20191203_1908_squashed_0006_auto_20191204_2129.py
wagtail_links/migrations/0006_auto_20200101_1646.py
wagtail_links/migrations/0007_auto_20200101_1658.py
wagtail_links/migrations/__init__.py
wagtail_links/models.py
wagtail_links/py.typed
wagtail_links/resolver.py
wagtail_links/templatetags/__init__.py
wagtail_links/templatetags/wagtail_links.py
wagtail_links/tests.py
wagtail_links-2.11.0.dist-info/LICENSE
wagtail_links-2.11.0.dist-info/METADATA
wagtail_links-2.11.0.dist-info/WHEEL
wagtail_links-2.11.0.dist-info/RECORD
