Metadata-Version: 2.3
Name: wagtail-links
Version: 2.11.0
Summary: Wagtail links provides a consistent way to refer to links in a wagtail page.
License: ISC
Author: thelab
Author-email: thelabdev@thelab.co
Requires-Python: >=3.11,<4.0
Classifier: License :: OSI Approved
Classifier: Programming Language :: Python :: 3
Classifier: Programming Language :: Python :: 3.11
Classifier: Programming Language :: Python :: 3.12
Classifier: Programming Language :: Python :: 3.13
Requires-Dist: django-stubs-ext (>=5.1.3,<6.0.0)
Requires-Dist: wagtail (>=6.3)
Project-URL: Homepage, https://gitlab.com/thelabnyc/wagtail-links
Project-URL: Repository, https://gitlab.com/thelabnyc/wagtail-links
